{
    "name" : "CIPeriodic Migration Test",
    "description" : "Tests a synchronizer migration with version upgrade from 0.1.9-snapshot.20240516.5948.0.v181a62a8 to the version on main; TODO(#11659) don't the hardcode version like that",
    "attribution-actor": "system",
    "parameters" : {
      "branch" : "main",
      "run-job": "deploy-ciperiodic-migration",
      "base-version": "181a62a824ed5fd9db8603a2e999ecb6e652ccb6"
    },
    "timetable" : {
      "per-hour" : 1,
      "hours-of-day": [
        2, 6, 10, 14, 18, 22
      ],
      "days-of-week" : [ "MON", "TUE", "WED", "THU", "FRI", "SAT", "SUN" ],
      "days-of-month" : [ ],
      "months" : [ "JAN", "FEB", "MAR", "APR", "MAY", "JUN", "JUL", "AUG", "SEP", "OCT", "NOV", "DEC" ]
    }
}
